Workbook

Sheet Estrategia y Arquitectura
A1: Plan Maestro de Yatoor: Producto, Arquitectura y Finanzas
A3: 1. Producto y Experiencia de Usuario (UX/UI)
A4: Mapa (Tab Izquierdo) | B4: Lienzo principal. Muestra puntos de interés cercanos (exploración libre) y la ruta activa (modo tour). Se apoya en geofencing (radios de 50 metros) para disparar audios o notificaciones al llegar a un punto, ahorrando batería.
A5: Yatoor (Tab Central) | B5: El cerebro de la app. Interfaz conversacional que devuelve tarjetas estructuradas (tiempo, distancia, paradas) y no textos largos.
A6: Perfil (Tab Derecho) | B6: Gestión de rutas guardadas (uso offline), logros desbloqueados y configuración de la audioguía.
A8: 2. La Arquitectura Híbrida (El Asesino de Costos)
A9: LLM con Caching Semántico | B9: No se llama a OpenAI/Anthropic para rutas obvias. Si un turista pide un tour clásico y hay un 95% de similitud con un pedido anterior, se le entrega el JSON cacheado (costo $0.00).
A10: Base de Datos Local (Nivel 1) | B10: Los 400 monumentos y museos principales de CABA viven en la base de datos (Supabase). No se paga por consultarlos.
A11: Mapbox y OSRM (Nivel 2) | B11: Se reemplaza a Google Maps por Mapbox para cargar los mapas base (25k usuarios gratis) y motores Open Source para trazar las rutas a pie gratis.
A12: Google Places On-Demand (Nivel 3) | B12: Solo se gatilla la API costosa de Google ($0.032 por búsqueda) cuando el bot necesita contexto en tiempo real ultra específico (ej. restaurantes abiertos ahora).
A14: 3. Modelo de Monetización: Freemium, B2C y B2B
A15: Travel Pass ($4.99) | B15: Pase premium por 7 días (IA ilimitada, uso 100% offline, audioguía). Evita el abandono de las suscripciones mensuales.
A16: Comisiones Integradas (Afiliados) | B16: Integración con plataformas de tickets (Tiqets, GetYourGuide). Margen puro del 8% al 15% por cada entrada vendida.
A17: Patrocinios Locales | B17: Cobro a comercios locales (gastronomía, cafés) para destacar sus pines en el mapa o ser priorizados contextualmente.

Sheet Costos Fijos
A1: Categoría | B1: Proveedor Sugerido | C1: Concepto | D1: Costo Mensual
A2: Licencias Stores | B2: Apple App Store / Google Play | C2: Programa de desarrolladores | D2: 10.41
A3: Base de Datos | B3: Supabase (Pro Tier) | C3: Alojamiento de usuarios y base de CABA | D3: 25
A4: Almacenamiento | B4: Supabase Storage / AWS S3 | C4: Hosting de imágenes y fotos | D4: 5
A5: Servidores | B5: Vercel | C5: Hosting del frontend y funciones IA | D5: 25
A6: Operaciones | B6: Namecheap + Resend | C6: Dominio web y correos (Auth) | D6: 5
A7: TOTAL FIJOS BASE | D7: =SUM(D2:D6) -> 70.41

Sheet Costos Variables Unitarios
A1: Categoría | B1: Concepto Detallado | C1: Métrica Unit. Estimada (Optimizada) | D1: Costo por Usuario (Mes)
A2: IA (Tokens) | B2: LLM Entrada/Salida (GPT-4o-mini / Claude Haiku) | C2: Absorbiendo el 80% de consultas vía Caché Semántico | D2: 0.0015
A3: Mapas (Ruteo) | B3: Mapbox Map Loads + SDK | C3: Descontando la capa gratuita y usando base local | D3: 0
A4: Mapas (POI) | B4: Google Places On-Demand + Mapbox Search | C4: Uso hiper-restringido a consultas dinámicas | D4: 0.001
A5: Datos Extras | B5: Lecturas y ancho de banda (AWS / Supabase) | C5: Escalable recién a partir del umbral gratuito | D5: 0
A6: TOTAL VARIABLE | B6: Por usuario activo al mes | D6: =SUM(D2:D5) -> 0.0025

Sheet Proyección y Break-Even
A1: PARÁMETROS DE INGRESOS | B1: Valor | C1: Detalle
A2: Precio Travel Pass (USD) | B2: 4.99 | C2: Pase premium por 7 días
A3: Comisión Tiendas (15%) | B3: =B2*0.15 -> 0.7485 | C3: Apple/Google Small Business Program
A4: Ingreso Neto por Pase | B4: =B2-B3 -> 4.2415 | C4: Margen real por cada venta
A6: Fase del Proyecto | B6: Usuarios (MAU) | C6: Costo Fijo Escalonado | D6: Costo Variable | E6: Costo Total (Arq. Híbrida) | F6: Ventas Necesarias (Break-Even) | G6: % Conversión Necesaria
A7: 1. MVP en CABA | B7: 500 | C7: ='Costos Fijos'!D7 -> 70.41 | D7: =B7*'Costos Variables Unitarios'!D6 -> 1.25 | E7: =C7+D7 -> 71.66 | F7: =ROUNDUP(E7/$B$4, 0) -> 17 | G7: =F7/B7 -> 0.034
A8: 2. Tracción Inicial | B8: 2500 | C8: ='Costos Fijos'!D7 -> 70.41 | D8: =B8*'Costos Variables Unitarios'!D6 -> 6.25 | E8: =C8+D8 -> 76.66 | F8: =ROUNDUP(E8/$B$4, 0) -> 19 | G8: =F8/B8 -> 0.0076
A9: 3. Validación | B9: 10000 | C9: ='Costos Fijos'!D7+15 -> 85.41 | D9: =B9*'Costos Variables Unitarios'!D6 -> 25 | E9: =C9+D9 -> 110.41 | F9: =ROUNDUP(E9/$B$4, 0) -> 27 | G9: =F9/B9 -> 0.0027
A10: 4. Crecimiento | B10: 50000 | C10: ='Costos Fijos'!D7+80 -> 150.41 | D10: =B10*'Costos Variables Unitarios'!D6 -> 125 | E10: =C10+D10 -> 275.41 | F10: =ROUNDUP(E10/$B$4, 0) -> 65 | G10: =F10/B10 -> 0.0013

Sheet Proyección de Ingresos Netos
A1: PARÁMETROS DEL MODELO | B1: Valor
A2: Precio del Travel Pass (PVP) | B2: 4.99
A3: Comisión Tiendas (15%) | B3: =B2*0.15 -> 0.7485
A4: Ingreso Neto por Venta | B4: =B2-B3 -> 4.2415
C6: ESCENARIO PESIMISTA (1.0%) | F6: ESCENARIO CONSERVADOR (2.5%) | I6: ESCENARIO OPTIMISTA (4.5%)
A7: Escala (MAU) | B7: Costo Infra | C7: Ventas | D7: Ingreso Neto | E7: Flujo de Caja | F7: Ventas | G7: Ingreso Neto | H7: Flujo de Caja | I7: Ventas | J7: Ingreso Neto | K7: Flujo de Caja
A8: 500 | B8: 60.8 | C8: =ROUND(500*0.01, 0) -> 5 | D8: =C8*$B$4 -> 21.2075 | E8: =D8-$B8 -> -39.5925 | F8: =ROUND(500*0.025, 0) -> 13 | G8: =F8*$B$4 -> 55.1395 | H8: =G8-$B8 -> -5.6605 | I8: =ROUND(500*0.045, 0) -> 23 | J8: =I8*$B$4 -> 97.5545 | K8: =J8-$B8 -> 36.7545
A9: 2500 | B9: 64 | C9: =ROUND(2500*0.01, 0) -> 25 | D9: =C9*$B$4 -> 106.0375 | E9: =D9-$B9 -> 42.0375 | F9: =ROUND(2500*0.025, 0) -> 63 | G9: =F9*$B$4 -> 267.2145 | H9: =G9-$B9 -> 203.2145 | I9: =ROUND(2500*0.045, 0) -> 113 | J9: =I9*$B$4 -> 479.2895 | K9: =J9-$B9 -> 415.2895
A10: 10000 | B10: 126 | C10: =ROUND(10000*0.01, 0) -> 100 | D10: =C10*$B$4 -> 424.15 | E10: =D10-$B10 -> 298.15 | F10: =ROUND(10000*0.025, 0) -> 250 | G10: =F10*$B$4 -> 1060.375 | H10: =G10-$B10 -> 934.375 | I10: =ROUND(10000*0.045, 0) -> 450 | J10: =I10*$B$4 -> 1908.675 | K10: =J10-$B10 -> 1782.675
A11: 50000 | B11: 342.5 | C11: =ROUND(50000*0.01, 0) -> 500 | D11: =C11*$B$4 -> 2120.75 | E11: =D11-$B11 -> 1778.25 | F11: =ROUND(50000*0.025, 0) -> 1250 | G11: =F11*$B$4 -> 5301.875 | H11: =G11-$B11 -> 4959.375 | I11: =ROUND(50000*0.045, 0) -> 2250 | J11: =I11*$B$4 -> 9543.375 | K11: =J11-$B11 -> 9200.875

Sheet Benchmark y Fuentes
A1: Categoría / Sector | B1: Tasa Promedio (%) | C1: Contexto de Mercado
A2: Apps Freemium Generales | B2: 2.0% - 5.0% | C2: El promedio estándar para apps de consumo masivo con compras integradas (IAP).
A3: Utilidades y Productividad | B3: 1.5% - 3.0% | C3: Suelen requerir que el usuario perciba un ahorro de tiempo inmediato.
A4: Apps de Viaje (Travel) | B4: 1.5% - 4.0% | C4: Tienen menor retención anual, pero la intención de pago es altísima en destino.
A5: Micropagos (< $5.00 USD) | B5: 3.0% - 6.0% | C5: Al superar la barrera del 'precio de un café', la fricción psicológica disminuye drásticamente.
A7: Fuente / Bibliografía (2026) | B7: Métrica Validada | C7: Justificación Rigurosa
A8: Reportes Freemium SaaS (Meegle, Bajaj Finserv) | B8: Conversión Freemium: 2% - 5% | C8: Establecen el estándar aceptado por la industria para la conversión Free-to-Paid en modelos de adopción masiva.
A9: UXCam Benchmarks (Travel) | B9: Conversión en Travel: 2.41% | C9: Sitúa la conversión de la categoría de Viajes/Turismo (Install-to-Purchase) en 2.41%, por encima de otras verticales generales.
A10: Global Subscription App Conversion Benchmarks | B10: Micropagos y Utilidad en Tiempo Real | C10: La alta conversión en turismo responde a la 'utilidad sensible al tiempo' (time-sensitive utility). El usuario paga por urgencia en destino.
